aistv/__init__.py
aistv/aistv.py
aistv/core.py
aistv/trainer.py
aistv-1.4.7.dist-info/METADATA
aistv-1.4.7.dist-info/WHEEL
aistv-1.4.7.dist-info/top_level.txt
aistv-1.4.7.dist-info/RECORD
