Metadata-Version: 2.4
Name: aistv
Version: 1.4.7
Summary: STV AI Chatbot Library for Python
Home-page: https://github.com/phuctrong1tuv
Author: Trọng Phúc
Author-email: Trọng Phúc <phuctrongytb16@gmail.com>
Project-URL: Discord, https://discord.gg/fTaCmdxG9H
Project-URL: TikTok, https://vm.tiktok.com/@aistvchat
Project-URL: GitHub, https://github.com/phuctrong1tuv
Keywords: chatbot,ai,stv,discord,tiktok
Requires-Python: >=3.8, <3.13
Requires-Dist: requests
Requires-Dist: groq
Requires-Dist: pydantic
Dynamic: author
Dynamic: home-page
Dynamic: requires-python
